operpy/__init__.py
operpy/bin_op.py
operpy/uni_op.py
operpy-0.1.1.dist-info/LICENSE
operpy-0.1.1.dist-info/METADATA
operpy-0.1.1.dist-info/WHEEL
operpy-0.1.1.dist-info/top_level.txt
operpy-0.1.1.dist-info/RECORD
