Metadata-Version: 2.1
Name: operpy
Version: 0.1.1
Summary: Package d'operation
Home-page: https://github.com/paul02prof/operpy
Author: Ninmegne Paul
Author-email: paul02prof@gmail.com
License: MIT
Classifier: Programming Language :: Python :: 3
Classifier: License :: OSI Approved :: MIT License
Classifier: Operating System :: OS Independent
Requires-Python: >=3.8
License-File: LICENSE
